cctrusted_vm/__init__.py
cctrusted_vm/cvm.py
cctrusted_vm/sdk.py
cctrusted_vm/tdx.py
cctrusted_vm-0.5.0.dist-info/METADATA
cctrusted_vm-0.5.0.dist-info/WHEEL
cctrusted_vm-0.5.0.dist-info/top_level.txt
cctrusted_vm-0.5.0.dist-info/RECORD
