Metadata-Version: 2.1
Name: cctrusted_vm
Version: 0.5.0
Summary: CC Trusted API VM SDK
Author-email: "Lu, Ken" <ken.lu@intel.com>, "Zhang, Wenhui" <wenhui.zhang@bytedance.com>
License: Apache Software License
Project-URL: Homepage, https://github.com/cc-api/cc-trusted-vmsdk
Project-URL: Bug Tracker, https://github.com/cc-api/cc-trusted-vmsdk/issues
Classifier: Programming Language :: Python :: 3
Classifier: License :: OSI Approved :: Apache Software License
Classifier: Operating System :: POSIX :: Linux
Requires-Python: >=3.6
Requires-Dist: cctrusted-base
Requires-Dist: pytest
